Saturn-0.3.5.dist-info/DESCRIPTION.rst
Saturn-0.3.5.dist-info/METADATA
Saturn-0.3.5.dist-info/RECORD
Saturn-0.3.5.dist-info/WHEEL
Saturn-0.3.5.dist-info/metadata.json
Saturn-0.3.5.dist-info/top_level.txt
saturn/__init__.py
saturn/from_arrow.py
saturn/saturn.py
saturn/tests.py
