Metadata-Version: 2.0
Name: Saturn
Version: 0.3.5
Summary: Simple functions for tz-aware datetimes.
Home-page: https://github.com/David-OConnor/saturn
Author: David O'Connor
Author-email: david.alan.oconnor@gmail.com
License: Apache 2.0
Keywords: datetime,pytz,timezone,tzinfo
Platform: UNKNOWN
Requires-Dist: pytz (>=2016.3)
